CHANGES.rst
LICENSE.rst
MANIFEST.in
README.rst
ez_setup.py
setup.py
CmtBasicModelingInterface.egg-info/PKG-INFO
CmtBasicModelingInterface.egg-info/SOURCES.txt
CmtBasicModelingInterface.egg-info/dependency_links.txt
CmtBasicModelingInterface.egg-info/entry_points.txt
CmtBasicModelingInterface.egg-info/namespace_packages.txt
CmtBasicModelingInterface.egg-info/requires.txt
CmtBasicModelingInterface.egg-info/top_level.txt
cmt/__init__.py
cmt/bmi/__init__.py
cmt/bmi/checker.py
cmt/bmi/interfaces.py
cmt/bmi/lint.py
cmt/bmi/examples/__init__.py
cmt/bmi/examples/diffusion/diff_2d.py
cmt/bmi/examples/water_tank/__init__.py
cmt/bmi/examples/water_tank/rain_in_tank.py
cmt/bmi/examples/water_tank/rainfall.py
cmt/bmi/examples/water_tank/water_tank.py
cmt/bmi/examples/water_tank/data/rainfall.txt
cmt/bmi/examples/water_tank/data/tank_info.cfg
cmt/bmi/tests/__init__.py
cmt/bmi/tests/test_checker.py
docs/faq.txt