Metadata-Version: 1.0
Name: CmtBasicModelingInterface
Version: 0.1.1
Summary: CSDMS Basic Modeling Interface
Home-page: https://csdms.colorado.edu
Author: Eric Hutton
Author-email: eric.hutton@colorado.edu
License: UNKNOWN
Platform: UNKNOWN
